hardware/src/alu.v
// =============================================================================
// NexaCPU — Arithmetic/Logic Unit (ALU)
// Milestone 1
// =============================================================================
//
// WHAT IS AN ALU?
// The ALU is the component that does all the actual computation in a CPU.
// Every ADD, SUB, AND, OR, NOT, and CMP instruction ultimately runs through
// this module. It's purely combinational — no clock, no memory. Given inputs
// A, B, and an operation code, it immediately produces a result and status flags.
//
// Because it's combinational, you can think of it as a collection of parallel
// circuits, all computing their results at the same time, with a multiplexer
// at the end selecting which result to pass through based on `op`.
//
// PORTS:
//   a       [15:0]  — first operand (from a register)
//   b       [15:0]  — second operand (from a register or immediate)
//   op      [3:0]   — operation selector (matches the ISA opcodes)
//   result  [15:0]  — computed output
//   zero    [1]     — flag: result == 0
//   negative[1]     — flag: result[15] == 1 (MSB set = negative in two's complement)
//   carry   [1]     — flag: arithmetic overflow / borrow
//
// =============================================================================

module alu (
    input  [15:0] a,          // Operand A — typically the value in rs1
    input  [15:0] b,          // Operand B — value in rs2, or sign-extended immediate
    input  [3:0]  op,         // Operation code — from the instruction's opcode field
    output reg [15:0] result, // The computed result — will be written to rd
    output zero,              // Zero flag: 1 if result is exactly 0
    output negative,          // Negative flag: 1 if result's MSB is 1
    output reg carry          // Carry flag: 1 on arithmetic carry/borrow
);

    // -------------------------------------------------------------------------
    // Operation constants — matching the NexaCPU ISA opcode table
    // Using `localparam` (local parameters) rather than magic numbers in the
    // case statement below. This is good practice: changing the ISA means
    // changing one definition here, not hunting through code.
    // -------------------------------------------------------------------------
    localparam OP_LOADI = 4'b0000; // Load immediate — ALU passes b through
    localparam OP_LOAD  = 4'b0001; // Load from memory — not computed in ALU
    localparam OP_STORE = 4'b0010; // Store to memory — not computed in ALU
    localparam OP_MOV   = 4'b0011; // Move — ALU passes b through
    localparam OP_ADD   = 4'b0100; // Addition
    localparam OP_SUB   = 4'b0101; // Subtraction
    localparam OP_AND   = 4'b0110; // Bitwise AND
    localparam OP_OR    = 4'b0111; // Bitwise OR
    localparam OP_NOT   = 4'b1000; // Bitwise NOT (unary, only uses a)
    localparam OP_CMP   = 4'b1001; // Compare — computes a-b for flags only

    // -------------------------------------------------------------------------
    // Combinational logic block
    //
    // `always @(*)` means: re-evaluate whenever ANY input signal changes.
    // The `*` is a shorthand for "sensitivity to everything this block reads."
    // This makes it combinational — no clock, no memory.
    //
    // `result` and `carry` are declared `reg` because they're assigned inside
    // an `always` block. This does NOT mean they are flip-flops — because this
    // block is not clocked, the synthesis tool will make them combinational.
    // -------------------------------------------------------------------------
    always @(*) begin
        carry  = 1'b0;   // default: no carry (overridden for ADD/SUB)
        result = 16'b0;  // default: zero (overridden by each case)

        case (op)

            // -- LOADI / MOV: pass the B operand straight through -----------
            // For LOADI: b is the sign-extended 6-bit immediate
            // For MOV:   the SOURCE register is encoded in rs1 position,
            //            so reg_a holds the value to copy (NOT reg_b/rs2).
            //            We pass `a` through for MOV, `b` for LOADI.
            OP_LOADI: begin
                result = b;
            end
            OP_MOV: begin
                result = a;   // MOV copies rs1 (a) into rd
            end

            // -- ADD ---------------------------------------------------------
            // We use a 17-bit wire for the addition so we can capture the
            // carry out of bit 15. The extra bit [16] is the carry.
            OP_ADD: begin
                {carry, result} = {1'b0, a} + {1'b0, b};
                // {carry, result} is Verilog concatenation — treating the two
                // as a single 17-bit value and splitting the result.
            end

            // -- SUB ---------------------------------------------------------
            // Subtraction: a - b. The carry flag here represents a borrow.
            // We compute it as a + (~b + 1) = a + two's complement of b.
            // The carry output from this is 1 when there is NO borrow (result >= 0).
            // We invert it to get a conventional "borrow" flag.
            OP_SUB: begin
                {carry, result} = {1'b0, a} - {1'b0, b};
                carry = ~carry; // invert: carry=1 means borrow occurred
            end

            // -- AND ---------------------------------------------------------
            OP_AND: begin
                result = a & b;
            end

            // -- OR ----------------------------------------------------------
            OP_OR: begin
                result = a | b;
            end

            // -- NOT ---------------------------------------------------------
            // Unary: only uses operand A. B is ignored.
            OP_NOT: begin
                result = ~a;
            end

            // -- CMP ---------------------------------------------------------
            // Compare sets flags by computing a - b, but the result is
            // NOT written to any register. Only the flags matter.
            // The control unit will suppress the register write for CMP.
            OP_CMP: begin
                result = a - b;
            end

            // -- LOAD / STORE / anything else --------------------------------
            // These instructions don't need the ALU to compute anything.
            // For LOAD/STORE, the address comes from a register directly —
            // we'll route that in the datapath, not here.
            // For unknown opcodes, default to 0 (safe fallback).
            default: begin
                result = 16'b0;
            end

        endcase
    end

    // -------------------------------------------------------------------------
    // Status flags — continuous assignments, always reflecting the current result
    //
    // These are wires driven by the result. They update instantly whenever
    // `result` changes — no clock needed.
    // -------------------------------------------------------------------------

    // Zero flag: 1 when every bit of result is 0
    assign zero     = (result == 16'b0);

    // Negative flag: 1 when the most significant bit is 1
    // In two's complement representation, MSB=1 means the number is negative
    assign negative = result[15];

endmodule

hardware/testbenches/alu_tb.v
// =============================================================================
// NexaCPU — ALU Testbench
// Milestone 1
// =============================================================================
//
// HOW TO READ A TESTBENCH:
// A testbench is a simulation harness — it has no ports (it's not a real chip),
// it just drives inputs and observes outputs. The `initial` block runs once at
// simulation time 0 and sequences through test cases using `#N` delays
// (wait N time units).
//
// We use `$display` to print results and `$finish` to end simulation.
// We check results manually (read the output) and also with `$error` assertions
// that will flag failures automatically.
//
// HOW TO RUN:
//   cd hardware
//   iverilog -o testbenches/alu_tb.vvp testbenches/alu_tb.v src/alu.v
//   vvp testbenches/alu_tb.vvp
//
// To generate a VCD waveform file (viewable in GTKWave):
//   The testbench already calls $dumpfile / $dumpvars — the file alu.vcd
//   will appear in the directory you run vvp from.
//
// =============================================================================

`timescale 1ns/1ps  // Time unit = 1 nanosecond, precision = 1 picosecond
                    // This affects how `#10` is interpreted in simulation.
                    // Doesn't matter much for functional tests, but good habit.

module alu_tb;

    // -------------------------------------------------------------------------
    // Declare signals to drive and observe
    //
    // Inputs to the ALU: declared as `reg` so we can assign them in `initial`
    // Outputs from the ALU: declared as `wire` (we observe, we don't drive)
    // -------------------------------------------------------------------------
    reg  [15:0] a;
    reg  [15:0] b;
    reg  [3:0]  op;
    wire [15:0] result;
    wire        zero;
    wire        negative;
    wire        carry;

    // -------------------------------------------------------------------------
    // Instantiate the ALU (the "Unit Under Test")
    //
    // Syntax: module_name instance_name (.port(signal), .port(signal), ...);
    // The .port_name(wire_name) syntax is called "named port connection" —
    // preferred over positional because it's immune to port reordering.
    // -------------------------------------------------------------------------
    alu uut (
        .a(a),
        .b(b),
        .op(op),
        .result(result),
        .zero(zero),
        .negative(negative),
        .carry(carry)
    );

    // -------------------------------------------------------------------------
    // Task: check_result
    //
    // A `task` is like a subroutine in Verilog — reusable code we can call
    // with different arguments. This one checks a result and prints pass/fail.
    // -------------------------------------------------------------------------
    integer test_num;
    integer pass_count;
    integer fail_count;

    task check;
        input [127:0] test_name;  // string label (packed bits used as string)
        input [15:0]  expected_result;
        input         expected_zero;
        input         expected_neg;
        begin
            test_num = test_num + 1;
            if (result === expected_result &&
                zero    === expected_zero   &&
                negative === expected_neg) begin
                $display("  PASS [%0d] %s | result=%0d z=%b n=%b",
                          test_num, test_name, result, zero, negative);
                pass_count = pass_count + 1;
            end else begin
                $display("  FAIL [%0d] %s", test_num, test_name);
                $display("       got:      result=%0d z=%b n=%b",
                          result, zero, negative);
                $display("       expected: result=%0d z=%b n=%b",
                          expected_result, expected_zero, expected_neg);
                fail_count = fail_count + 1;
            end
        end
    endtask

    // -------------------------------------------------------------------------
    // Main test sequence
    // -------------------------------------------------------------------------
    initial begin
        // Set up VCD dump so we can view this in GTKWave
        $dumpfile("alu.vcd");
        $dumpvars(0, alu_tb);   // dump all signals in this module and below

        test_num   = 0;
        pass_count = 0;
        fail_count = 0;

        $display("============================================");
        $display("  NexaCPU ALU Testbench — Milestone 1");
        $display("============================================");

        // ---- LOADI (op=0000) -----------------------------------------------
        $display("\n-- LOADI (pass B through) --");
        op = 4'b0000; a = 16'd0;
        b = 16'd5;    #10; check("LOADI  5", 16'd5,   1'b0, 1'b0);
        b = 16'd0;    #10; check("LOADI  0", 16'd0,   1'b1, 1'b0);
        b = 16'd63;   #10; check("LOADI 63", 16'd63,  1'b0, 1'b0);

        // ---- MOV (op=0011) -------------------------------------------------
        // MOV copies rs1 (operand A) to rd. Set a=42, b is irrelevant.
        $display("\n-- MOV (pass A through) --");
        op = 4'b0011;
        a = 16'd42; b = 16'd0;
        #10; check("MOV 42",   16'd42,  1'b0, 1'b0);

        // ---- ADD (op=0100) -------------------------------------------------
        $display("\n-- ADD --");
        op = 4'b0100;
        a = 16'd10;  b = 16'd20; #10; check("10+20",    16'd30,    1'b0, 1'b0);
        a = 16'd0;   b = 16'd0;  #10; check("0+0",      16'd0,     1'b1, 1'b0);
        a = 16'd255; b = 16'd1;  #10; check("255+1",    16'd256,   1'b0, 1'b0);
        // Overflow: 65535 + 1 should set carry and result = 0
        a = 16'hFFFF; b = 16'd1; #10;
        if (result === 16'd0 && carry === 1'b1) begin
            $display("  PASS [%0d] ADD overflow: result=0, carry=1", test_num+1);
            pass_count = pass_count + 1;
        end else begin
            $display("  FAIL [%0d] ADD overflow: got result=%0d carry=%b", test_num+1, result, carry);
            fail_count = fail_count + 1;
        end
        test_num = test_num + 1;

        // ---- SUB (op=0101) -------------------------------------------------
        $display("\n-- SUB --");
        op = 4'b0101;
        a = 16'd20;  b = 16'd10; #10; check("20-10",   16'd10,  1'b0, 1'b0);
        a = 16'd5;   b = 16'd5;  #10; check("5-5=0",   16'd0,   1'b1, 1'b0);
        // Negative result: 3-10 = -7, which in 16-bit two's complement is 0xFFF9
        // MSB will be 1, so negative flag should be set
        a = 16'd3;   b = 16'd10; #10;
        if (result[15] === 1'b1 && zero === 1'b0) begin
            $display("  PASS [%0d] SUB negative: result=%0d (0x%h), neg=1", test_num+1, $signed(result), result);
            pass_count = pass_count + 1;
        end else begin
            $display("  FAIL [%0d] SUB negative: got result=%0d neg=%b", test_num+1, result, negative);
            fail_count = fail_count + 1;
        end
        test_num = test_num + 1;

        // ---- AND (op=0110) -------------------------------------------------
        $display("\n-- AND --");
        op = 4'b0110;
        a = 16'b1111_0000_1111_0000;
        b = 16'b1010_1010_1010_1010;
        #10; check("AND pattern", 16'b1010_0000_1010_0000, 1'b0, 1'b1);
        a = 16'hFFFF; b = 16'h0000; #10; check("AND x&0=0", 16'h0000, 1'b1, 1'b0);
        a = 16'hFFFF; b = 16'hFFFF; #10; check("AND x&x=x", 16'hFFFF, 1'b0, 1'b1);

        // ---- OR (op=0111) --------------------------------------------------
        $display("\n-- OR --");
        op = 4'b0111;
        a = 16'b1010_0000_0000_0000;
        b = 16'b0000_0000_0000_0101;
        #10; check("OR pattern", 16'b1010_0000_0000_0101, 1'b0, 1'b1);
        a = 16'h0000; b = 16'h0000; #10; check("OR 0|0=0", 16'h0000, 1'b1, 1'b0);

        // ---- NOT (op=1000) -------------------------------------------------
        $display("\n-- NOT --");
        op = 4'b1000;
        a = 16'h0000; b = 16'hXXXX; // B is irrelevant for NOT
        #10; check("NOT 0=FFFF", 16'hFFFF, 1'b0, 1'b1);
        a = 16'hFFFF;
        #10; check("NOT FFFF=0", 16'h0000, 1'b1, 1'b0);
        a = 16'h00FF;
        #10; check("NOT 00FF=FF00", 16'hFF00, 1'b0, 1'b1);

        // ---- CMP (op=1001) — only flags matter, result not used -----------
        $display("\n-- CMP (flags only) --");
        op = 4'b1001;
        // Equal values: result = 0, zero should be set
        a = 16'd42; b = 16'd42; #10;
        if (zero === 1'b1 && negative === 1'b0) begin
            $display("  PASS [%0d] CMP equal: z=1, n=0", test_num+1);
            pass_count = pass_count + 1;
        end else begin
            $display("  FAIL [%0d] CMP equal: got z=%b n=%b", test_num+1, zero, negative);
            fail_count = fail_count + 1;
        end
        test_num = test_num + 1;
        // a < b: result negative
        a = 16'd3; b = 16'd10; #10;
        if (zero === 1'b0 && negative === 1'b1) begin
            $display("  PASS [%0d] CMP less: z=0, n=1", test_num+1);
            pass_count = pass_count + 1;
        end else begin
            $display("  FAIL [%0d] CMP less: got z=%b n=%b", test_num+1, zero, negative);
            fail_count = fail_count + 1;
        end
        test_num = test_num + 1;
        // a > b: result positive
        a = 16'd10; b = 16'd3; #10;
        if (zero === 1'b0 && negative === 1'b0) begin
            $display("  PASS [%0d] CMP greater: z=0, n=0", test_num+1);
            pass_count = pass_count + 1;
        end else begin
            $display("  FAIL [%0d] CMP greater: got z=%b n=%b", test_num+1, zero, negative);
            fail_count = fail_count + 1;
        end
        test_num = test_num + 1;

        // ---- Final report --------------------------------------------------
        $display("\n============================================");
        $display("  Results: %0d passed, %0d failed (of %0d)",
                  pass_count, fail_count, test_num);
        if (fail_count == 0)
            $display("  ALL TESTS PASSED — ALU verified. ✓");
        else
            $display("  SOME TESTS FAILED — check output above.");
        $display("============================================");

        $finish;
    end

    // -------------------------------------------------------------------------
    // Optional: monitor — prints a line every time any signal changes.
    // Useful for debugging, can be noisy. Comment out when not needed.
    // -------------------------------------------------------------------------
    // initial begin
    //     $monitor("t=%0t op=%b a=%0d b=%0d | result=%0d z=%b n=%b c=%b",
    //               $time, op, a, b, result, zero, negative, carry);
    // end

endmodule

waveforms/alu.vcd
$date
	Wed Jul 22 00:49:08 2026
$end
$version
	Icarus Verilog
$end
$timescale
	1ps
$end
$scope module alu_tb $end
$var wire 1 ! zero $end
$var wire 16 " result [15:0] $end
$var wire 1 # negative $end
$var wire 1 $ carry $end
$var reg 16 % a [15:0] $end
$var reg 16 & b [15:0] $end
$var reg 4 ' op [3:0] $end
$var integer 32 ( fail_count [31:0] $end
$var integer 32 ) pass_count [31:0] $end
$var integer 32 * test_num [31:0] $end
$scope module uut $end
$var wire 16 + a [15:0] $end
$var wire 16 , b [15:0] $end
$var wire 4 - op [3:0] $end
$var wire 1 ! zero $end
$var wire 1 # negative $end
$var parameter 4 . OP_ADD $end
$var parameter 4 / OP_AND $end
$var parameter 4 0 OP_CMP $end
$var parameter 4 1 OP_LOAD $end
$var parameter 4 2 OP_LOADI $end
$var parameter 4 3 OP_MOV $end
$var parameter 4 4 OP_NOT $end
$var parameter 4 5 OP_OR $end
$var parameter 4 6 OP_STORE $end
$var parameter 4 7 OP_SUB $end
$var reg 1 $ carry $end
$var reg 16 8 result [15:0] $end
$upscope $end
$scope task check $end
$var reg 1 9 expected_neg $end
$var reg 16 : expected_result [15:0] $end
$var reg 1 ; expected_zero $end
$var reg 128 < test_name [127:0] $end
$upscope $end
$upscope $end
$enddefinitions $end
$comment Show the parameter values. $end
$dumpall
b101 7
b10 6
b111 5
b1000 4
b11 3
b0 2
b1 1
b1001 0
b110 /
b100 .
$end
#0
$dumpvars
bx <
x;
bx :
x9
b101 8
b0 -
b101 ,
b0 +
b0 *
b0 )
b0 (
b0 '
b101 &
b0 %
0$
0#
b101 "
0!
$end
#10000
1!
b0 "
b0 8
b0 &
b0 ,
b1 )
b1 *
09
0;
b101 :
b100110001001111010000010100010001001001001000000010000000110101 <
#20000
0!
b111111 "
b111111 8
b111111 &
b111111 ,
b10 )
b10 *
1;
b0 :
b100110001001111010000010100010001001001001000000010000000110000 <
#30000
0!
b101010 "
b101010 8
b0 &
b0 ,
b101010 %
b101010 +
b11 '
b11 -
b11 )
b11 *
0;
b111111 :
b100110001001111010000010100010001001001001000000011011000110011 <
#40000
0!
b11110 "
b11110 8
b10100 &
b10100 ,
b1010 %
b1010 +
b100 '
b100 -
b100 )
b100 *
b101010 :
b10011010100111101010110001000000011010000110010 <
#50000
1!
b0 "
b0 8
b0 &
b0 ,
b0 %
b0 +
b101 )
b101 *
b11110 :
b11000100110000001010110011001000110000 <
#60000
0!
b100000000 "
b100000000 8
b1 &
b1 ,
b11111111 %
b11111111 +
b110 )
b110 *
1;
b0 :
b1100000010101100110000 <
#70000
1$
1!
b0 "
b0 8
b1111111111111111 %
b1111111111111111 +
b111 )
b111 *
0;
b100000000 :
b11001000110101001101010010101100110001 <
#80000
0!
b1010 "
b1010 8
1$
b1010 &
b1010 ,
b10100 %
b10100 +
b101 '
b101 -
b1000 *
b1000 )
#90000
1!
b0 "
b0 8
1$
b101 &
b101 ,
b101 %
b101 +
b1001 )
b1001 *
b1010 :
b11001000110000001011010011000100110000 <
#100000
1#
0!
b1111111111111001 "
b1111111111111001 8
0$
b1010 &
b1010 ,
b11 %
b11 +
b1010 )
b1010 *
1;
b0 :
b11010100101101001101010011110100110000 <
#110000
0!
b1010000010100000 "
b1010000010100000 8
b1010101010101010 &
b1010101010101010 ,
b1111000011110000 %
b1111000011110000 +
b110 '
b110 -
b1011 *
b1011 )
#120000
0#
1!
b0 "
b0 8
b0 &
b0 ,
b1111111111111111 %
b1111111111111111 +
b1100 )
b1100 *
19
0;
b1010000010100000 :
b100000101001110010001000010000001110000011000010111010001110100011001010111001001101110 <
#130000
1#
0!
b1111111111111111 "
b1111111111111111 8
b1111111111111111 &
b1111111111111111 ,
b1101 )
b1101 *
09
1;
b0 :
b10000010100111001000100001000000111100000100110001100000011110100110000 <
#140000
0!
b1010000000000101 "
b1010000000000101 8
b101 &
b101 ,
b1010000000000000 %
b1010000000000000 +
b111 '
b111 -
b1110 )
b1110 *
19
0;
b1111111111111111 :
b10000010100111001000100001000000111100000100110011110000011110101111000 <
#150000
0#
1!
b0 "
b0 8
b0 &
b0 ,
b0 %
b0 +
b1111 )
b1111 *
b1010000000000101 :
b1001111010100100010000001110000011000010111010001110100011001010111001001101110 <
#160000
1#
0!
b1111111111111111 "
b1111111111111111 8
bx &
bx ,
b1000 '
b1000 -
b10000 )
b10000 *
09
1;
b0 :
b100111101010010001000000011000001111100001100000011110100110000 <
#170000
0#
1!
b0 "
b0 8
b1111111111111111 %
b1111111111111111 +
b10001 )
b10001 *
19
0;
b1111111111111111 :
b1001110010011110101010000100000001100000011110101000110010001100100011001000110 <
#180000
1#
0!
b1111111100000000 "
b1111111100000000 8
b11111111 %
b11111111 +
b10010 )
b10010 *
09
1;
b0 :
b1001110010011110101010000100000010001100100011001000110010001100011110100110000 <
#190000
0#
1!
b0 "
b0 8
b101010 &
b101010 ,
b101010 %
b101010 +
b1001 '
b1001 -
b10011 )
b10011 *
19
0;
b1111111100000000 :
b1001110010011110101010000100000001100000011000001000110010001100011110101000110010001100011000000110000 <
#200000
1#
0!
b1111111111111001 "
b1111111111111001 8
b1010 &
b1010 ,
b11 %
b11 +
b10100 *
b10100 )
#210000
0#
0!
b111 "
b111 8
b11 &
b11 ,
b1010 %
b1010 +
b10101 *
b10101 )
#220000
b10110 *
b10110 )
