hardware/src/control_unit.v
// =============================================================================
// NexaCPU — Control Unit
// Milestone 4
// =============================================================================
//
// WHAT IS THE CONTROL UNIT?
// The control unit is the "conductor" of the CPU. It takes the 16-bit
// instruction fetched from memory, decodes it, and generates a set of control
// signals that tell every other module what to do this cycle.
//
// It doesn't compute anything itself — it just reads the instruction bits and
// sets a collection of true/false (1-bit) output signals:
//   - Should the ALU add? Or subtract? Or do a bitwise AND?
//   - Should we write the ALU result to a register?
//   - Should we read from data memory? Or write to it?
//   - Should the PC jump to a new address, or just increment?
//
// Think of it as a lookup table: "for instruction opcode X, here are the
// exact switch settings for every other part of the CPU."
//
// WHY THIS IS THE CONCEPTUAL HEART:
// Every design choice made in the ISA (our instruction table) directly
// manifests here. The control unit is where abstract instruction definitions
// become concrete wiring decisions. Understanding this module means
// understanding how the CPU executes programs.
//
// INPUTS:
//   instr    [15:0] — the current instruction from instruction memory
//   zero     [1]    — Zero flag from the ALU (for conditional branches)
//   negative [1]    — Negative flag from the ALU
//
// OUTPUTS (control signals — all combinational):
//   alu_op   [3:0]  — which ALU operation to perform (passed straight through)
//   alu_src  [1]    — ALU B input source: 0=register, 1=immediate value
//   reg_write[1]    — 1 = write ALU result to destination register
//   mem_read [1]    — 1 = read from data memory this cycle
//   mem_write[1]    — 1 = write to data memory this cycle
//   mem_to_reg[1]   — 1 = write memory read result to register (LOAD)
//                     0 = write ALU result to register
//   pc_src   [1]    — 1 = jump (load new PC), 0 = increment PC
//   pc_next  [5:0]  — the jump target address (from instruction immediate field)
//   rd       [2:0]  — destination register address (from instruction)
//   rs1      [2:0]  — source register 1 address
//   rs2      [2:0]  — source register 2 address
//   imm6     [5:0]  — 6-bit immediate value (sign-extended to 16 bits externally)
//   halt     [1]    — 1 = HALT instruction, stop everything
//
// =============================================================================

module control_unit (
    input  [15:0] instr,       // Current instruction
    input         zero,        // ALU Zero flag (for BEQ/BNE)
    input         negative,    // ALU Negative flag (for BLT)

    // Decoded instruction fields (passed to datapath)
    output [2:0]  rd,          // Destination register
    output [2:0]  rs1,         // Source register 1
    output [2:0]  rs2,         // Source register 2
    output [5:0]  imm6,        // 6-bit immediate

    // ALU control
    output [3:0]  alu_op,      // Which ALU operation
    output        alu_src,     // B input: 0=rs2 value, 1=imm6 (zero-extended)

    // Register file control
    output        reg_write,   // 1 = write result to rd
    output        mem_to_reg,  // 1 = result comes from memory (LOAD), 0 = from ALU

    // Data memory control
    output        mem_read,    // 1 = read data memory
    output        mem_write,   // 1 = write data memory

    // PC control
    output        pc_src,      // 1 = jump/branch taken, 0 = PC+1
    output [5:0]  pc_next,     // Jump target address

    // Halt
    output        halt         // 1 = stop the CPU
);

    // -------------------------------------------------------------------------
    // Extract instruction fields — purely combinational bit-slicing
    //
    // This is just wiring: each output is permanently connected to a slice
    // of the instruction register. No logic, just routing.
    // -------------------------------------------------------------------------
    assign rd   = instr[11:9];   // Destination register (bits 11-9)
    assign rs1  = instr[8:6];    // Source register 1   (bits 8-6)
    assign rs2  = instr[2:0];    // Source register 2   (bits 2-0)
    assign imm6 = instr[5:0];    // 6-bit immediate     (bits 5-0)

    // The opcode is the top 4 bits
    wire [3:0] opcode = instr[15:12];

    // The ALU operation code IS the opcode — we designed the ISA this way
    // deliberately, so no translation table is needed. The ALU's op input
    // directly matches the instruction's opcode field.
    assign alu_op = opcode;

    // -------------------------------------------------------------------------
    // Opcode constants (same as in alu.v — duplicated here for readability)
    // -------------------------------------------------------------------------
    localparam OP_LOADI = 4'b0000;
    localparam OP_LOAD  = 4'b0001;
    localparam OP_STORE = 4'b0010;
    localparam OP_MOV   = 4'b0011;
    localparam OP_ADD   = 4'b0100;
    localparam OP_SUB   = 4'b0101;
    localparam OP_AND   = 4'b0110;
    localparam OP_OR    = 4'b0111;
    localparam OP_NOT   = 4'b1000;
    localparam OP_CMP   = 4'b1001;
    localparam OP_JMP   = 4'b1010;
    localparam OP_BEQ   = 4'b1011;
    localparam OP_BNE   = 4'b1100;
    localparam OP_BLT   = 4'b1101;
    localparam OP_HALT  = 4'b1111;

    // -------------------------------------------------------------------------
    // Control signal generation — fully combinational
    //
    // For each control output, we use a continuous assign with a conditional
    // expression. Read each line as: "this signal is 1 when the opcode is X".
    //
    // This is equivalent to a truth table or a ROM lookup:
    //   opcode → set of control bits
    // -------------------------------------------------------------------------

    // ALU source: use the immediate value (not rs2) for LOADI, LOAD, and branches
    // For LOADI: b = imm6 (the value to load)
    // For LOAD:  b = imm6 (could also be rs1-based — we use rs1 for address)
    // For STORE: not strictly needed, but harmless
    assign alu_src = (opcode == OP_LOADI) ||
                     (opcode == OP_LOAD)  ||
                     (opcode == OP_STORE) ||
                     (opcode == OP_JMP)   ||
                     (opcode == OP_BEQ)   ||
                     (opcode == OP_BNE)   ||
                     (opcode == OP_BLT);

    // Register write: 1 for all instructions that produce a result in rd
    // NOT for: STORE (writes memory), CMP (flags only), JMP/branches (no result),
    //          HALT (nothing)
    assign reg_write = (opcode == OP_LOADI) ||
                       (opcode == OP_LOAD)  ||
                       (opcode == OP_MOV)   ||
                       (opcode == OP_ADD)   ||
                       (opcode == OP_SUB)   ||
                       (opcode == OP_AND)   ||
                       (opcode == OP_OR)    ||
                       (opcode == OP_NOT);
    // CMP: no reg write (flags only)
    // STORE, JMP, BEQ, BNE, BLT, HALT: no reg write

    // Result source: LOAD gets its write-back value from memory, not the ALU
    assign mem_to_reg = (opcode == OP_LOAD);

    // Data memory read: only LOAD reads from data memory
    assign mem_read   = (opcode == OP_LOAD);

    // Data memory write: only STORE writes to data memory
    assign mem_write  = (opcode == OP_STORE);

    // PC source: jump if it's JMP, or if it's a conditional branch whose
    // condition is met:
    //   BEQ: branch if Zero=1 (last comparison was equal)
    //   BNE: branch if Zero=0 (last comparison was not equal)
    //   BLT: branch if Negative=1 (last comparison, a < b)
    assign pc_src = (opcode == OP_JMP)                    ||
                    (opcode == OP_BEQ && zero == 1'b1)    ||
                    (opcode == OP_BNE && zero == 1'b0)    ||
                    (opcode == OP_BLT && negative == 1'b1);

    // The jump target is always the imm6 field
    // (for branches AND JMP — our 6-bit ISA uses the immediate as the address)
    assign pc_next = imm6;

    // Halt: stop execution
    assign halt = (opcode == OP_HALT);

endmodule

hardware/testbenches/control_unit_tb.v
// =============================================================================
// NexaCPU — Control Unit Testbench
// Milestone 4
// =============================================================================
//
// HOW TO RUN (from C:\Projects\NexaCPU):
//   iverilog -o hardware/testbenches/control_unit_tb.vvp \
//            hardware/testbenches/control_unit_tb.v \
//            hardware/src/control_unit.v
//   vvp hardware/testbenches/control_unit_tb.vvp
//
// WHAT THIS TESTS:
//   For every opcode in the ISA, verify that the control unit generates the
//   correct set of control signals. This is the most important test in Phase 1
//   because an incorrect control signal silently misbehaves at runtime —
//   e.g. reg_write=1 on a STORE instruction would corrupt a register.
//
// =============================================================================

`timescale 1ns/1ps

module control_unit_tb;

    // Inputs
    reg  [15:0] instr;
    reg         zero, negative;

    // Outputs
    wire [2:0]  rd, rs1, rs2;
    wire [5:0]  imm6;
    wire [3:0]  alu_op;
    wire        alu_src, reg_write, mem_to_reg, mem_read, mem_write;
    wire        pc_src;
    wire [5:0]  pc_next;
    wire        halt;

    // Instantiate
    control_unit uut (
        .instr(instr), .zero(zero), .negative(negative),
        .rd(rd), .rs1(rs1), .rs2(rs2), .imm6(imm6),
        .alu_op(alu_op), .alu_src(alu_src),
        .reg_write(reg_write), .mem_to_reg(mem_to_reg),
        .mem_read(mem_read), .mem_write(mem_write),
        .pc_src(pc_src), .pc_next(pc_next),
        .halt(halt)
    );

    integer pass_count, fail_count, test_num;

    // Helper task: check a single 1-bit control signal
    task check1;
        input [127:0] name;
        input         got, expected;
        begin
            test_num = test_num + 1;
            if (got === expected) begin
                $display("    PASS [%0d] %s = %b", test_num, name, got);
                pass_count = pass_count + 1;
            end else begin
                $display("    FAIL [%0d] %s: got %b, expected %b", test_num, name, got, expected);
                fail_count = fail_count + 1;
            end
        end
    endtask

    // Build a full instruction word from fields
    function [15:0] make_instr;
        input [3:0] op;
        input [2:0] rd_f, rs1_f;
        input [5:0] imm_rs2;
        begin
            make_instr = {op, rd_f, rs1_f, imm_rs2};
        end
    endfunction

    initial begin
        $dumpfile("control_unit.vcd");
        $dumpvars(0, control_unit_tb);

        pass_count = 0; fail_count = 0; test_num = 0;
        zero = 0; negative = 0;

        $display("============================================");
        $display("  NexaCPU Control Unit Testbench — M4");
        $display("============================================");

        // ---- LOADI R1, 5 ---------------------------------------------------
        $display("\n-- LOADI R1, 5 --");
        instr = 16'h0205; // 0000_001_000_000101
        #5;
        check1("alu_src   (1=imm)", alu_src,   1'b1);
        check1("reg_write (1)",     reg_write, 1'b1);
        check1("mem_read  (0)",     mem_read,  1'b0);
        check1("mem_write (0)",     mem_write, 1'b0);
        check1("mem_to_reg(0)",     mem_to_reg,1'b0);
        check1("pc_src    (0)",     pc_src,    1'b0);
        check1("halt      (0)",     halt,      1'b0);

        // ---- ADD R3, R1, R2 ------------------------------------------------
        $display("\n-- ADD R3, R1, R2 --");
        instr = make_instr(4'b0100, 3'd3, 3'd1, 6'd2);
        #5;
        check1("alu_src   (0=reg)", alu_src,   1'b0);
        check1("reg_write (1)",     reg_write, 1'b1);
        check1("mem_read  (0)",     mem_read,  1'b0);
        check1("mem_write (0)",     mem_write, 1'b0);
        check1("pc_src    (0)",     pc_src,    1'b0);
        check1("halt      (0)",     halt,      1'b0);

        // ---- LOAD R2, R1 (load from mem[R1] into R2) -----------------------
        $display("\n-- LOAD R2, R1 --");
        instr = make_instr(4'b0001, 3'd2, 3'd1, 6'd0);
        #5;
        check1("mem_read  (1)",     mem_read,  1'b1);
        check1("mem_write (0)",     mem_write, 1'b0);
        check1("reg_write (1)",     reg_write, 1'b1);
        check1("mem_to_reg(1)",     mem_to_reg,1'b1);
        check1("pc_src    (0)",     pc_src,    1'b0);

        // ---- STORE R1, R2 (store R2 to mem[R1]) ----------------------------
        $display("\n-- STORE R1, R2 --");
        instr = make_instr(4'b0010, 3'd0, 3'd1, 6'd2);
        #5;
        check1("mem_write (1)",     mem_write, 1'b1);
        check1("mem_read  (0)",     mem_read,  1'b0);
        check1("reg_write (0)",     reg_write, 1'b0);
        check1("pc_src    (0)",     pc_src,    1'b0);

        // ---- CMP R1, R2 ----------------------------------------------------
        $display("\n-- CMP R1, R2 --");
        instr = make_instr(4'b1001, 3'd0, 3'd1, 6'd2);
        #5;
        check1("reg_write (0)",     reg_write, 1'b0);  // CMP does NOT write to a register
        check1("mem_read  (0)",     mem_read,  1'b0);
        check1("mem_write (0)",     mem_write, 1'b0);
        check1("pc_src    (0)",     pc_src,    1'b0);

        // ---- JMP 15 --------------------------------------------------------
        $display("\n-- JMP 15 --");
        instr = make_instr(4'b1010, 3'd0, 3'd0, 6'd15);
        #5;
        check1("pc_src    (1)",     pc_src,    1'b1);  // always jump
        check1("reg_write (0)",     reg_write, 1'b0);
        check1("mem_write (0)",     mem_write, 1'b0);
        test_num = test_num + 1;
        if (pc_next === 6'd15) begin
            $display("    PASS [%0d] pc_next = %0d", test_num, pc_next);
            pass_count = pass_count + 1;
        end else begin
            $display("    FAIL [%0d] pc_next: got %0d, expected 15", test_num, pc_next);
            fail_count = fail_count + 1;
        end

        // ---- BEQ 8 with zero=1 (branch taken) ------------------------------
        $display("\n-- BEQ 8 (zero=1, branch taken) --");
        instr = make_instr(4'b1011, 3'd0, 3'd0, 6'd8);
        zero = 1; negative = 0; #5;
        check1("pc_src (1=taken)",  pc_src, 1'b1);

        // ---- BEQ 8 with zero=0 (branch not taken) --------------------------
        $display("\n-- BEQ 8 (zero=0, not taken) --");
        zero = 0; #5;
        check1("pc_src (0=not taken)", pc_src, 1'b0);

        // ---- BNE 8 with zero=0 (branch taken) ------------------------------
        $display("\n-- BNE 8 (zero=0, branch taken) --");
        instr = make_instr(4'b1100, 3'd0, 3'd0, 6'd8);
        zero = 0; negative = 0; #5;
        check1("pc_src (1=taken)",  pc_src, 1'b1);

        // ---- BNE 8 with zero=1 (not taken) ---------------------------------
        $display("\n-- BNE 8 (zero=1, not taken) --");
        zero = 1; #5;
        check1("pc_src (0=not taken)", pc_src, 1'b0);

        // ---- BLT 5 with negative=1 (taken) ---------------------------------
        $display("\n-- BLT 5 (negative=1, taken) --");
        instr = make_instr(4'b1101, 3'd0, 3'd0, 6'd5);
        zero = 0; negative = 1; #5;
        check1("pc_src (1=taken)",  pc_src, 1'b1);

        // ---- BLT 5 with negative=0 (not taken) -----------------------------
        $display("\n-- BLT 5 (negative=0, not taken) --");
        negative = 0; #5;
        check1("pc_src (0=not taken)", pc_src, 1'b0);

        // ---- HALT ----------------------------------------------------------
        $display("\n-- HALT --");
        instr = 16'hF000;
        zero = 0; negative = 0; #5;
        check1("halt      (1)",     halt,      1'b1);
        check1("reg_write (0)",     reg_write, 1'b0);
        check1("mem_write (0)",     mem_write, 1'b0);
        check1("pc_src    (0)",     pc_src,    1'b0);

        // ---- Verify field extraction ----------------------------------------
        $display("\n-- Field extraction --");
        // LOADI R3, 42: opcode=0000, rd=011, rs1=000, imm6=101010
        instr = {4'b0000, 3'b011, 3'b000, 6'b101010};
        #5;
        test_num = test_num + 1;
        if (rd === 3'd3 && rs1 === 3'd0 && imm6 === 6'b101010) begin
            $display("  PASS [%0d] Fields: rd=%0d rs1=%0d imm6=%0d",
                      test_num, rd, rs1, imm6);
            pass_count = pass_count + 1;
        end else begin
            $display("  FAIL [%0d] Fields: rd=%0d rs1=%0d imm6=%0d (expected 3,0,42)",
                      test_num, rd, rs1, imm6);
            fail_count = fail_count + 1;
        end

        // ---- Final ----------------------------------------------------------
        $display("\n============================================");
        $display("  Results: %0d passed, %0d failed (of %0d)",
                  pass_count, fail_count, test_num);
        if (fail_count == 0)
            $display("  ALL TESTS PASSED — Control Unit verified. ✓");
        else
            $display("  SOME TESTS FAILED.");
        $display("============================================");
        $finish;
    end

endmodule

waveforms/control_unit.vcd
$date
	Wed Jul 22 00:38:39 2026
$end
$version
	Icarus Verilog
$end
$timescale
	1ps
$end
$scope module control_unit_tb $end
$var wire 3 ! rs2 [2:0] $end
$var wire 3 " rs1 [2:0] $end
$var wire 1 # reg_write $end
$var wire 3 $ rd [2:0] $end
$var wire 1 % pc_src $end
$var wire 6 & pc_next [5:0] $end
$var wire 1 ' mem_write $end
$var wire 1 ( mem_to_reg $end
$var wire 1 ) mem_read $end
$var wire 6 * imm6 [5:0] $end
$var wire 1 + halt $end
$var wire 1 , alu_src $end
$var wire 4 - alu_op [3:0] $end
$var reg 16 . instr [15:0] $end
$var reg 1 / negative $end
$var reg 1 0 zero $end
$var integer 32 1 fail_count [31:0] $end
$var integer 32 2 pass_count [31:0] $end
$var integer 32 3 test_num [31:0] $end
$scope function make_instr $end
$var reg 6 4 imm_rs2 [5:0] $end
$var reg 4 5 op [3:0] $end
$var reg 3 6 rd_f [2:0] $end
$var reg 3 7 rs1_f [2:0] $end
$upscope $end
$scope module uut $end
$var wire 4 8 alu_op [3:0] $end
$var wire 1 , alu_src $end
$var wire 16 9 instr [15:0] $end
$var wire 1 / negative $end
$var wire 6 : pc_next [5:0] $end
$var wire 1 % pc_src $end
$var wire 1 # reg_write $end
$var wire 1 0 zero $end
$var wire 3 ; rs2 [2:0] $end
$var wire 3 < rs1 [2:0] $end
$var wire 3 = rd [2:0] $end
$var wire 4 > opcode [3:0] $end
$var wire 1 ' mem_write $end
$var wire 1 ( mem_to_reg $end
$var wire 1 ) mem_read $end
$var wire 6 ? imm6 [5:0] $end
$var wire 1 + halt $end
$var parameter 4 @ OP_ADD $end
$var parameter 4 A OP_AND $end
$var parameter 4 B OP_BEQ $end
$var parameter 4 C OP_BLT $end
$var parameter 4 D OP_BNE $end
$var parameter 4 E OP_CMP $end
$var parameter 4 F OP_HALT $end
$var parameter 4 G OP_JMP $end
$var parameter 4 H OP_LOAD $end
$var parameter 4 I OP_LOADI $end
$var parameter 4 J OP_MOV $end
$var parameter 4 K OP_NOT $end
$var parameter 4 L OP_OR $end
$var parameter 4 M OP_STORE $end
$var parameter 4 N OP_SUB $end
$upscope $end
$scope task check1 $end
$var reg 1 O expected $end
$var reg 1 P got $end
$var reg 128 Q name [127:0] $end
$upscope $end
$upscope $end
$enddefinitions $end
$comment Show the parameter values. $end
$dumpall
b101 N
b10 M
b111 L
b1000 K
b11 J
b0 I
b1 H
b1010 G
b1111 F
b1001 E
b1100 D
b1101 C
b1011 B
b110 A
b100 @
$end
#0
$dumpvars
bx Q
xP
xO
b101 ?
b0 >
b1 =
b0 <
b101 ;
b101 :
b1000000101 9
b0 8
bx 7
bx 6
bx 5
bx 4
b0 3
b0 2
b0 1
00
0/
b1000000101 .
b0 -
1,
0+
b101 *
0)
0(
0'
b101 &
0%
b1 $
1#
b0 "
b101 !
$end
#5000
0,
b11 $
b11 =
b1 "
b1 <
b10 !
b10 ;
b10 &
b10 :
b10 *
b10 ?
b100 -
b100 8
b100 >
b100011001000010 .
b100011001000010 9
b100 5
b11 6
b1 7
b10 4
b111 2
b111 3
0O
0P
b1101000011000010110110001110100001000000010000000100000001000000010000000100000001010000011000000101001 Q
#10000
1,
1#
b10 $
b10 =
b0 !
b0 ;
b0 &
b0 :
b0 *
b0 ?
1(
1)
b1 -
b1 8
b1 >
b1010001000000 .
b1010001000000 9
b1 5
b10 6
b0 4
0O
0P
b1101 2
b1101 3
b1101000011000010110110001110100001000000010000000100000001000000010000000100000001010000011000000101001 Q
#15000
0#
b0 $
b0 =
b10 !
b10 ;
b10 &
b10 :
b10 *
b10 ?
0(
0)
1'
b10 -
b10 8
b10 >
b10000001000010 .
b10000001000010 9
b10 5
b0 6
b10 4
b10010 2
b10010 3
0O
0P
b1110000011000110101111101110011011100100110001100100000001000000010000000100000001010000011000000101001 Q
#20000
0,
0'
b1001 -
b1001 8
b1001 >
b1001000001000010 .
b1001000001000010 9
b1001 5
b10110 2
b10110 3
0O
0P
b1110000011000110101111101110011011100100110001100100000001000000010000000100000001010000011000000101001 Q
#25000
1,
1%
b0 "
b0 <
b111 !
b111 ;
b1111 &
b1111 :
b1111 *
b1111 ?
b1010 -
b1010 8
b1010 >
b1010000000001111 .
b1010000000001111 9
b1010 5
b0 7
b1111 4
b11010 2
b11010 3
b1110000011000110101111101110011011100100110001100100000001000000010000000100000001010000011000000101001 Q
#30000
b0 !
b0 ;
b1000 &
b1000 :
b1000 *
b1000 ?
b1011 -
b1011 8
b1011 >
10
b1011000000001000 .
b1011000000001000 9
b1011 5
b1000 4
b11110 2
b11110 3
0O
0P
b1101101011001010110110101011111011101110111001001101001011101000110010100100000001010000011000000101001 Q
#35000
0%
00
b11111 2
b11111 3
1O
1P
b1110000011000110101111101110011011100100110001100100000001010000011000100111101011101000110000101101011011001010110111000101001 Q
#40000
1%
b1100 -
b1100 8
b1100 >
b1100000000001000 .
b1100000000001000 9
b1100 5
b100000 2
b100000 3
0O
0P
b1110010011000110010000000101000001100000011110101101110011011110111010000100000011101000110000101101011011001010110111000101001 Q
#45000
0%
10
b100001 2
b100001 3
1O
1P
b1110000011000110101111101110011011100100110001100100000001010000011000100111101011101000110000101101011011001010110111000101001 Q
#50000
1%
b101 !
b101 ;
b101 &
b101 :
b101 *
b101 ?
b1101 -
b1101 8
b1101 >
1/
00
b1101000000000101 .
b1101000000000101 9
b1101 5
b101 4
b100010 2
b100010 3
0O
0P
b1110010011000110010000000101000001100000011110101101110011011110111010000100000011101000110000101101011011001010110111000101001 Q
#55000
0%
0/
b100011 2
b100011 3
1O
1P
b1110000011000110101111101110011011100100110001100100000001010000011000100111101011101000110000101101011011001010110111000101001 Q
#60000
0,
b0 !
b0 ;
b0 &
b0 :
b0 *
b0 ?
1+
b1111 -
b1111 8
b1111 >
b1111000000000000 .
b1111000000000000 9
b100100 2
b100100 3
0O
0P
b1110010011000110010000000101000001100000011110101101110011011110111010000100000011101000110000101101011011001010110111000101001 Q
#65000
1#
1,
b11 $
b11 =
b10 !
b10 ;
b101010 &
b101010 :
b101010 *
b101010 ?
0+
b0 -
b0 8
b0 >
b11000101010 .
b11000101010 9
b101000 2
b101000 3
0O
0P
b1110000011000110101111101110011011100100110001100100000001000000010000000100000001010000011000000101001 Q
#70000
b101001 2
b101001 3
