hardware/src/data_memory.v
// =============================================================================
// NexaCPU — Data Memory (RAM)
// Milestone 5
// =============================================================================
//
// WHAT IS DATA MEMORY?
// This is the RAM — the read/write memory the CPU uses to store and retrieve
// program data (variables, arrays, the stack). Unlike instruction memory
// (which is read-only ROM), data memory can be both read and written.
//
// HARVARD vs VON NEUMANN — WHY SEPARATE MEMORIES:
// In a Harvard architecture, instruction memory and data memory are completely
// separate — different address spaces, different buses, accessed independently.
// Von Neumann uses a single shared memory for everything.
//
// We chose Harvard for these reasons:
//   1. SIMPLICITY: No arbitration needed. The CPU can simultaneously fetch an
//      instruction AND read/write data in the same cycle. With shared memory,
//      only one operation can happen per cycle.
//   2. EDUCATIONAL CLARITY: It makes the datapath diagram cleaner — there's
//      an obvious "instruction bus" and "data bus", which matches how textbooks
//      typically introduce CPUs.
//   3. FPGA PRACTICALITY: Modern FPGAs have dual-port block RAMs that map
//      naturally to Harvard architecture.
//
// SIZE: 64 locations × 16 bits = 128 bytes of data memory.
// Same depth as instruction memory, sufficient for our test programs.
//
// WRITE BEHAVIOR: Synchronous (clocked on posedge)
//   Data written takes effect on the next clock edge — same as registers.
//
// READ BEHAVIOR: Combinational (immediate, like instruction memory)
//   The read result is available within the same cycle it's requested.
//   This is called "asynchronous read" or "transparent read" — it's fine for
//   simulation and for FPGAs that support it (Vivado handles this correctly).
//
// =============================================================================

module data_memory (
    input        clk,          // Clock — writes are synchronous
    input  [5:0] addr,         // 6-bit address (64 locations)
    input  [15:0] wr_data,     // Data to write
    input        wr_en,        // 1 = write this cycle
    input        rd_en,        // 1 = read this cycle (gates the output)
    output [15:0] rd_data      // Data read from memory
);

    // The RAM array: 64 × 16-bit entries
    reg [15:0] mem [0:63];

    // Initialize to zero (important for predictable simulation behavior)
    integer i;
    initial begin
        for (i = 0; i < 64; i = i + 1)
            mem[i] = 16'b0;
    end

    // ---- Synchronous write ------------------------------------------------
    always @(posedge clk) begin
        if (wr_en)
            mem[addr] <= wr_data;
    end

    // ---- Combinational read -----------------------------------------------
    // If rd_en=0, output 0 (not driving anything onto the data bus).
    // If rd_en=1, output the value at `addr`.
    assign rd_data = rd_en ? mem[addr] : 16'b0;

endmodule

hardware/testbenches/data_memory_tb.v
// =============================================================================
// NexaCPU — Data Memory Testbench
// Milestone 5
// =============================================================================
`timescale 1ns/1ps

module data_memory_tb;

    reg        clk, wr_en, rd_en;
    reg  [5:0] addr;
    reg  [15:0] wr_data;
    wire [15:0] rd_data;

    data_memory uut (.clk(clk), .addr(addr), .wr_data(wr_data),
                     .wr_en(wr_en), .rd_en(rd_en), .rd_data(rd_data));

    initial clk = 0;
    always #5 clk = ~clk;

    integer pass_count, fail_count, test_num;

    task check16;
        input [127:0] label;
        input [15:0] got;
        input [15:0] expected;
        begin
            test_num = test_num + 1;
            if (got === expected) begin
                $display("  PASS [%0d] %s = %0d", test_num, label, got);
                pass_count = pass_count + 1;
            end else begin
                $display("  FAIL [%0d] %s: got %0d, expected %0d", test_num, label, got, expected);
                fail_count = fail_count + 1;
            end
        end
    endtask

    task tick;
        begin
            @(posedge clk); #1;
        end
    endtask

    initial begin
        $dumpfile("data_memory.vcd");
        $dumpvars(0, data_memory_tb);
        pass_count = 0; fail_count = 0; test_num = 0;
        wr_en = 0; rd_en = 0; addr = 0; wr_data = 0;

        $display("============================================");
        $display("  NexaCPU Data Memory Testbench — M5");
        $display("============================================");

        // Initial state: all zeros
        $display("\n-- Initial state (all zero) --");
        rd_en = 1; addr = 0; #1; check16("mem[0] initially", rd_data, 16'd0);
        addr = 63; #1;          check16("mem[63] initially", rd_data, 16'd0);

        // Write and read back
        $display("\n-- Write and read back --");
        addr = 5; wr_data = 16'd42; wr_en = 1; tick; wr_en = 0;
        addr = 5; rd_en = 1; #1;   check16("mem[5]=42", rd_data, 16'd42);

        addr = 63; wr_data = 16'd1234; wr_en = 1; tick; wr_en = 0;
        addr = 63; #1;               check16("mem[63]=1234", rd_data, 16'd1234);

        // rd_en=0 returns 0
        $display("\n-- rd_en gating --");
        rd_en = 0; addr = 5; #1;
        check16("rd_en=0 gives 0", rd_data, 16'd0);

        // Write without read enable doesn't disturb other locations
        $display("\n-- Write isolation --");
        rd_en = 1; addr = 6; wr_data = 16'd99; wr_en = 1; tick; wr_en = 0;
        addr = 5; #1; check16("mem[5] unchanged after write to [6]", rd_data, 16'd42);
        addr = 6; #1; check16("mem[6]=99", rd_data, 16'd99);

        // Overwrite
        $display("\n-- Overwrite --");
        addr = 5; wr_data = 16'd777; wr_en = 1; tick; wr_en = 0;
        addr = 5; #1; check16("mem[5] overwritten to 777", rd_data, 16'd777);

        $display("\n============================================");
        $display("  Results: %0d passed, %0d failed (of %0d)",
                  pass_count, fail_count, test_num);
        if (fail_count == 0)
            $display("  ALL TESTS PASSED — Data Memory verified. ✓");
        else
            $display("  SOME TESTS FAILED.");
        $display("============================================");
        $finish;
    end
endmodule

waveforms/data_memory.vcd
$date
	Wed Jul 22 00:41:51 2026
$end
$version
	Icarus Verilog
$end
$timescale
	1ps
$end
$scope module data_memory_tb $end
$var wire 16 ! rd_data [15:0] $end
$var reg 6 " addr [5:0] $end
$var reg 1 # clk $end
$var reg 1 $ rd_en $end
$var reg 16 % wr_data [15:0] $end
$var reg 1 & wr_en $end
$var integer 32 ' fail_count [31:0] $end
$var integer 32 ( pass_count [31:0] $end
$var integer 32 ) test_num [31:0] $end
$scope module uut $end
$var wire 6 * addr [5:0] $end
$var wire 1 # clk $end
$var wire 1 $ rd_en $end
$var wire 16 + wr_data [15:0] $end
$var wire 1 & wr_en $end
$var wire 16 , rd_data [15:0] $end
$var integer 32 - i [31:0] $end
$upscope $end
$scope task check16 $end
$var reg 16 . expected [15:0] $end
$var reg 16 / got [15:0] $end
$var reg 128 0 label [127:0] $end
$upscope $end
$scope task tick $end
$upscope $end
$upscope $end
$enddefinitions $end
$comment Show the parameter values. $end
$dumpall
$end
#0
$dumpvars
bx 0
bx /
bx .
b1000000 -
b0 ,
b0 +
b0 *
b0 )
b0 (
b0 '
0&
b0 %
1$
0#
b0 "
b0 !
$end
#1000
b111111 "
b111111 *
b1 (
b1 )
b0 .
b0 /
b1101101011001010110110101011011001100000101110100100000011010010110111001101001011101000110100101100001011011000110110001111001 0
#2000
1&
b101010 %
b101010 +
b101 "
b101 *
b10 (
b10 )
b1100101011011010101101100110110001100110101110100100000011010010110111001101001011101000110100101100001011011000110110001111001 0
#5000
b101010 !
b101010 ,
1#
#6000
0&
#7000
b0 !
b0 ,
1&
b10011010010 %
b10011010010 +
b111111 "
b111111 *
b11 (
b11 )
b101010 .
b101010 /
b11011010110010101101101010110110011010101011101001111010011010000110010 0
#10000
0#
#15000
b10011010010 !
b10011010010 ,
1#
#16000
0&
#17000
b0 !
b0 ,
b101 "
b101 *
0$
b100 (
b100 )
b10011010010 .
b10011010010 /
b11011010110010101101101010110110011011000110011010111010011110100110001001100100011001100110100 0
#18000
1&
b1100011 %
b1100011 +
b110 "
b110 *
1$
b101 (
b101 )
b0 .
b0 /
b11100100110010001011111011001010110111000111101001100000010000001100111011010010111011001100101011100110010000000110000 0
#20000
0#
#25000
b1100011 !
b1100011 ,
1#
#26000
b101010 !
b101010 ,
b101 "
b101 *
0&
#27000
b1100011 !
b1100011 ,
b110 "
b110 *
b110 (
b110 )
b101010 .
b101010 /
b1110100011001010111001000100000011101110111001001101001011101000110010100100000011101000110111100100000010110110011011001011101 0
#28000
b101010 !
b101010 ,
1&
b1100001001 %
b1100001001 +
b101 "
b101 *
b111 (
b111 )
b1100011 .
b1100011 /
b11011010110010101101101010110110011011001011101001111010011100100111001 0
#30000
0#
#35000
b1100001001 !
b1100001001 ,
1#
#36000
0&
#37000
b1000 (
b1000 )
b1100001001 .
b1100001001 /
b1100101011100100111011101110010011010010111010001110100011001010110111000100000011101000110111100100000001101110011011100110111 0
