hardware/src/instruction_memory.v
// =============================================================================
// NexaCPU — Instruction Memory (ROM)
// Milestone 3
// =============================================================================
//
// WHAT IS INSTRUCTION MEMORY?
// This is a read-only memory (ROM) that holds the program — the sequence of
// 16-bit instructions the CPU will execute. It's "read-only" because programs
// don't modify themselves; only data memory (Milestone 5) is read/write.
//
// This is the HARVARD ARCHITECTURE choice: instruction memory and data memory
// are completely separate. The alternative (von Neumann) uses one memory for
// both, which requires more careful arbitration. Harvard is simpler for a
// first CPU and is what most embedded/microcontroller architectures use.
//
// HOW PROGRAMS BECOME BINARY:
// The CPU can only understand binary — a sequence of 1s and 0s. A program
// written as assembly ("LOADI R1, 5") needs to be "assembled" into the binary
// encoding from our ISA table. For Milestones 3–7, we hand-assemble programs.
// Milestone 8 automates this with a Python assembler.
//
// The assembled program is stored in a `.mem` file — a plain text file where
// each line is one instruction in hexadecimal. Icarus Verilog can load this
// directly at simulation time using the `$readmemh` system task.
//
// PORTS:
//   pc    [5:0]   — address from the program counter (which instruction to fetch)
//   instr [15:0]  — the instruction at that address (sent to the control unit)
//
// =============================================================================

module instruction_memory (
    input  [5:0]  pc,       // Instruction address (from PC)
    output [15:0] instr     // Instruction bits (to control unit + datapath)
);

    // -------------------------------------------------------------------------
    // The memory array: 64 locations, each 16 bits
    // 64 entries × 16 bits = 128 bytes of program space
    // -------------------------------------------------------------------------
    reg [15:0] mem [0:63];

    // -------------------------------------------------------------------------
    // Load program from file at simulation startup
    //
    // `$readmemh` reads a hex file into the memory array.
    // The path is relative to where you run the simulation from.
    // We use a parameter so the testbench can override the file path.
    //
    // In the full CPU (cpu.v), the top-level will pass the real program file.
    // For isolated testing, we use the test program below.
    // -------------------------------------------------------------------------
    parameter MEM_FILE = "hardware/programs/test_imem.mem";

    initial begin
        $readmemh(MEM_FILE, mem);
    end

    // -------------------------------------------------------------------------
    // Combinational read — instruction is available immediately from PC address
    // Instruction memory reads are not clocked: the PC value goes in,
    // the instruction comes out in the same cycle (within propagation delay).
    // -------------------------------------------------------------------------
    assign instr = mem[pc];

endmodule

hardware/src/program_counter.v
// =============================================================================
// NexaCPU — Program Counter
// Milestone 3
// =============================================================================
//
// WHAT IS THE PROGRAM COUNTER?
// The Program Counter (PC) is a single register that holds the address of the
// NEXT instruction to fetch. It's the CPU's "bookmark" — it tracks where in
// the program we are.
//
// Every clock cycle, one of three things happens to the PC:
//   1. Reset: PC goes to 0 (start of program)
//   2. Load (jump/branch): PC gets a new address from the instruction
//   3. Increment: PC advances by 1 (fetch the next sequential instruction)
//
// The PC is 6 bits wide — matching our 6-bit immediate field, which means
// programs can be up to 64 instructions long (addresses 0–63).
// That's enough for meaningful programs while keeping the design simple.
//
// =============================================================================

module program_counter (
    input        clk,         // Clock
    input        rst,         // Synchronous reset — PC → 0
    input        load,        // 1 = jump: load `next_pc` into PC
    input  [5:0] next_pc,     // Address to jump to (from instruction)
    output reg [5:0] pc       // Current PC value (fed to instruction memory)
);

    // On every rising clock edge:
    always @(posedge clk) begin
        if (rst)
            pc <= 6'd0;          // Reset: go to address 0
        else if (load)
            pc <= next_pc;       // Jump: take the new address
        else
            pc <= pc + 6'd1;     // Normal: advance to next instruction
    end

    // NOTE: pc + 1 wraps around when it hits 63 → 0 (6-bit overflow).
    // This is fine — HALT stops execution before we reach address 63 in practice.

endmodule

hardware/testbenches/program_counter_tb.v
// =============================================================================
// NexaCPU — Program Counter + Instruction Memory Testbench
// Milestone 3
// =============================================================================
//
// HOW TO RUN (from C:\Projects\NexaCPU):
//   iverilog -o hardware/testbenches/program_counter_tb.vvp \
//            hardware/testbenches/program_counter_tb.v \
//            hardware/src/program_counter.v \
//            hardware/src/instruction_memory.v
//   vvp hardware/testbenches/program_counter_tb.vvp
//
// WHAT THIS TESTS:
//   1. PC starts at 0 after reset
//   2. PC increments by 1 each clock cycle
//   3. PC can be loaded with an arbitrary value (jump)
//   4. Instruction memory returns the correct 16-bit instruction for each PC
//   5. Sequence: reset → fetch 4 instructions in order, checking each value
//
// =============================================================================

`timescale 1ns/1ps

module program_counter_tb;

    reg        clk, rst, load;
    reg  [5:0] next_pc;
    wire [5:0] pc;
    wire [15:0] instr;

    // Instantiate PC
    program_counter pc_inst (
        .clk(clk), .rst(rst),
        .load(load), .next_pc(next_pc),
        .pc(pc)
    );

    // Instantiate instruction memory — point at our test program
    instruction_memory #(.MEM_FILE("hardware/programs/test_imem.mem")) imem (
        .pc(pc),
        .instr(instr)
    );

    // Clock: 10ns period
    initial clk = 0;
    always #5 clk = ~clk;

    integer pass_count, fail_count, test_num;

    task check_pc_instr;
        input [5:0]  exp_pc;
        input [15:0] exp_instr;
        input [63:0] label;
        begin
            test_num = test_num + 1;
            if (pc === exp_pc && instr === exp_instr) begin
                $display("  PASS [%0d] %s: PC=%0d instr=0x%04X",
                          test_num, label, pc, instr);
                pass_count = pass_count + 1;
            end else begin
                $display("  FAIL [%0d] %s: got PC=%0d instr=0x%04X, expected PC=%0d instr=0x%04X",
                          test_num, label, pc, instr, exp_pc, exp_instr);
                fail_count = fail_count + 1;
            end
        end
    endtask

    initial begin
        $dumpfile("program_counter.vcd");
        $dumpvars(0, program_counter_tb);

        pass_count = 0; fail_count = 0; test_num = 0;
        load = 0; next_pc = 0;

        $display("============================================");
        $display("  NexaCPU PC + IMEM Testbench — M3");
        $display("============================================");

        // ---- Reset ----------------------------------------------------------
        $display("\n-- Reset --");
        rst = 1; @(posedge clk); #1;
        rst = 0;
        // PC should be 0, instruction should be test_imem.mem[0] = 0x0205 (LOADI R1,5)
        check_pc_instr(6'd0, 16'h0205, "After reset");

        // ---- Sequential fetch: PC increments each cycle --------------------
        $display("\n-- Sequential fetch --");
        @(posedge clk); #1;
        check_pc_instr(6'd1, 16'h040A, "Cycle 1 (LOADI R2,10)");

        @(posedge clk); #1;
        check_pc_instr(6'd2, 16'h4642, "Cycle 2 (ADD R3,R1,R2)");

        @(posedge clk); #1;
        check_pc_instr(6'd3, 16'hF000, "Cycle 3 (HALT)");

        // ---- Jump (load) ---------------------------------------------------
        $display("\n-- Jump to address 1 --");
        load = 1; next_pc = 6'd1;
        @(posedge clk); #1;
        load = 0;
        check_pc_instr(6'd1, 16'h040A, "After jump to 1");

        // ---- Jump to 0 (restart) -------------------------------------------
        load = 1; next_pc = 6'd0;
        @(posedge clk); #1;
        load = 0;
        check_pc_instr(6'd0, 16'h0205, "After jump to 0 (restart)");

        // ---- Resume incrementing after jump --------------------------------
        @(posedge clk); #1;
        check_pc_instr(6'd1, 16'h040A, "Resume increment after jump");

        // ---- Final ----------------------------------------------------------
        $display("\n============================================");
        $display("  Results: %0d passed, %0d failed (of %0d)",
                  pass_count, fail_count, test_num);
        if (fail_count == 0)
            $display("  ALL TESTS PASSED — PC + IMEM verified. ✓");
        else
            $display("  SOME TESTS FAILED.");
        $display("============================================");
        $finish;
    end

endmodule

waveforms/program_counter.vcd
$date
	Wed Jul 22 00:36:32 2026
$end
$version
	Icarus Verilog
$end
$timescale
	1ps
$end
$scope module program_counter_tb $end
$var wire 6 ! pc [5:0] $end
$var wire 16 " instr [15:0] $end
$var reg 1 # clk $end
$var reg 1 $ load $end
$var reg 6 % next_pc [5:0] $end
$var reg 1 & rst $end
$var integer 32 ' fail_count [31:0] $end
$var integer 32 ( pass_count [31:0] $end
$var integer 32 ) test_num [31:0] $end
$scope module imem $end
$var wire 16 * instr [15:0] $end
$var wire 6 + pc [5:0] $end
$var parameter 248 , MEM_FILE $end
$upscope $end
$scope module pc_inst $end
$var wire 1 # clk $end
$var wire 1 $ load $end
$var wire 6 - next_pc [5:0] $end
$var wire 1 & rst $end
$var reg 6 . pc [5:0] $end
$upscope $end
$scope task check_pc_instr $end
$var reg 16 / exp_instr [15:0] $end
$var reg 6 0 exp_pc [5:0] $end
$var reg 64 1 label [63:0] $end
$upscope $end
$upscope $end
$enddefinitions $end
$comment Show the parameter values. $end
$dumpall
b1101000011000010111001001100100011101110110000101110010011001010010111101110000011100100110111101100111011100100110000101101101011100110010111101110100011001010111001101110100010111110110100101101101011001010110110100101110011011010110010101101101 ,
$end
#0
$dumpvars
bx 1
bx 0
bx /
bx .
b0 -
bx +
bx *
b0 )
b0 (
b0 '
1&
b0 %
0$
0#
bx "
bx !
$end
#5000
b1000000101 "
b1000000101 *
b0 !
b0 +
b0 .
1#
#6000
b1 (
b1 )
b110010101110010001000000111001001100101011100110110010101110100 1
b1000000101 /
b0 0
0&
#10000
0#
#15000
b10000001010 "
b10000001010 *
b1 !
b1 +
b1 .
1#
#16000
b10 (
b10 )
b100100100100000010100100011001000101100001100010011000000101001 1
b10000001010 /
b1 0
#20000
0#
#25000
b100011001000010 "
b100011001000010 *
b10 !
b10 +
b10 .
1#
#26000
b11 (
b11 )
b11001100101100010100100011000100101100010100100011001000101001 1
b100011001000010 /
b10 0
#30000
0#
#35000
b1111000000000000 "
b1111000000000000 *
b11 !
b11 +
b11 .
1#
#36000
b1 %
b1 -
1$
b100 (
b100 )
b11001100100000001010000100100001000001010011000101010000101001 1
b1111000000000000 /
b11 0
#40000
0#
#45000
b10000001010 "
b10000001010 *
b1 !
b1 +
b1 .
1#
#46000
b0 %
b0 -
b101 (
b101 )
b111010101101101011100000010000001110100011011110010000000110001 1
b10000001010 /
b1 0
1$
#50000
0#
#55000
b1000000101 "
b1000000101 *
b0 !
b0 +
b0 .
1#
#56000
b110 (
b110 )
b111001001100101011100110111010001100001011100100111010000101001 1
b1000000101 /
b0 0
0$
#60000
0#
#65000
b10000001010 "
b10000001010 *
b1 !
b1 +
b1 .
1#
#66000
b111 (
b111 )
b111010001100101011100100010000001101010011101010110110101110000 1
b10000001010 /
b1 0
