hardware/src/register_file.v
// =============================================================================
// NexaCPU — Register File
// Milestone 2
// =============================================================================
//
// WHAT IS A REGISTER FILE?
// The register file is the CPU's "scratch pad" — a small, extremely fast bank
// of storage locations that sit right next to the ALU. NexaCPU has 8 registers,
// R0–R7, each 16 bits wide. Instructions name their operands by register number
// ("R1", "R3") rather than memory addresses, because registers are faster than
// memory by orders of magnitude.
//
// WHY THIS MILESTONE MATTERS — THE CLOCK:
// This is your first clocked module. Unlike the ALU (which is purely
// combinational — inputs in, outputs out, no memory), a register file has
// state — it remembers values between clock cycles.
//
// The rule: reads are combinational (instant), writes are clocked (synchronized).
// This mirrors real hardware: you can read a register's value at any time,
// but writing a new value only "takes hold" at the rising edge of the clock.
//
// WHY CLOCKED WRITES?
// If writes were combinational, the register value could change mid-cycle while
// the ALU is using it as an input, causing glitches. Clocking the write
// guarantees that a register's value is stable for the entire cycle, and only
// changes at the defined tick boundary. This predictability is what makes
// synchronous digital design manageable.
//
// PORTS:
//   clk        — the clock signal (shared by the whole CPU)
//   rst        — synchronous reset: clears all registers to 0 on next clock edge
//   rd_addr1   — read port 1 address (which register to read for operand A)
//   rd_data1   — read port 1 data output (value of that register)
//   rd_addr2   — read port 2 address (operand B)
//   rd_data2   — read port 2 data output
//   wr_addr    — write address (destination register rd)
//   wr_data    — data to write
//   wr_en      — write enable: 1 = perform write, 0 = do nothing
//
// TWO READ PORTS, ONE WRITE PORT:
// Most ALU instructions need two source registers simultaneously (e.g. ADD R3, R1, R2
// needs R1 and R2 at the same time). So we have two independent read ports.
// We only need one write port because each instruction writes at most one result.
//
// =============================================================================

module register_file (
    input        clk,         // Clock — writes happen on posedge
    input        rst,         // Synchronous reset — all regs → 0

    // Read port 1 (for rs1 / operand A)
    input  [2:0] rd_addr1,    // Which register to read (0–7)
    output [15:0] rd_data1,   // The value in that register

    // Read port 2 (for rs2 / operand B)
    input  [2:0] rd_addr2,    // Which register to read
    output [15:0] rd_data2,   // The value in that register

    // Write port (for rd / result)
    input  [2:0] wr_addr,     // Which register to write
    input  [15:0] wr_data,    // Value to write
    input        wr_en        // 1 = write this cycle, 0 = don't
);

    // -------------------------------------------------------------------------
    // The actual storage: 8 registers, each 16 bits wide
    //
    // In Verilog, a 2D array like this is declared as:
    //   reg [width-1:0] name [0:count-1]
    // Here: 16-bit wide, 8 entries (indices 0–7)
    // -------------------------------------------------------------------------
    reg [15:0] regs [0:7];

    // -------------------------------------------------------------------------
    // Clocked write logic (and reset)
    //
    // This always block fires on every rising clock edge.
    // Two behaviors:
    //   1. Reset: if rst is high, clear every register to 0.
    //   2. Write: if wr_en is high and wr_addr is not R0, write wr_data.
    //
    // WHY SYNCHRONOUS RESET?
    // We check `rst` inside the posedge block rather than adding it to the
    // sensitivity list as `always @(posedge clk or posedge rst)` (asynchronous).
    // Synchronous reset is simpler to reason about and works well for FPGA.
    //
    // R0 IS HARDWIRED TO ZERO:
    // Writing to R0 is silently discarded. Reading R0 always returns 0.
    // This is a classic RISC design choice — having a guaranteed-zero register
    // simplifies many common operations (e.g. `LOADI R0, 5` is a no-op,
    // `SUB Rx, Ry, R0` is a copy, `CMP Rx, R0` checks if Rx is zero).
    // -------------------------------------------------------------------------
    integer i;

    always @(posedge clk) begin
        if (rst) begin
            // Reset: clear all registers. The `for` loop here describes
            // parallel reset logic, not a sequential loop — synthesis will
            // generate simultaneous reset for every register.
            for (i = 0; i < 8; i = i + 1)
                regs[i] <= 16'b0;
        end else if (wr_en && wr_addr != 3'd0) begin
            // Normal write: only if enabled, and not targeting R0
            // `<=` is non-blocking assignment — correct for clocked logic
            regs[wr_addr] <= wr_data;
        end
        // If wr_en=0, nothing changes — the register retains its value.
        // This is the "memory" behavior flip-flops give us.
    end

    // -------------------------------------------------------------------------
    // Combinational read logic
    //
    // Reads are NOT clocked — they are continuous combinational outputs.
    // The moment rd_addr1 changes, rd_data1 updates immediately (same cycle).
    // This is necessary because the CPU needs register values available
    // before the clock edge where it uses them.
    //
    // R0 special case: always reads as 0, regardless of what's stored.
    // -------------------------------------------------------------------------
    assign rd_data1 = (rd_addr1 == 3'd0) ? 16'b0 : regs[rd_addr1];
    assign rd_data2 = (rd_addr2 == 3'd0) ? 16'b0 : regs[rd_addr2];

    // -------------------------------------------------------------------------
    // READ-DURING-WRITE behavior:
    // If you write to a register and read from it in the same clock cycle,
    // the read returns the OLD value (before the write takes effect).
    // This is "write-then-read" latency = 1 cycle, standard for synchronous designs.
    // The control unit is designed with this in mind.
    // -------------------------------------------------------------------------

endmodule

hardware/testbenches/register_file_tb.v
// =============================================================================
// NexaCPU — Register File Testbench
// Milestone 2
// =============================================================================
//
// HOW TO RUN:
//   cd C:\Projects\NexaCPU
//   $env:PATH += ";C:\iverilog\bin;C:\iverilog\gtkwave\bin"
//   iverilog -o hardware/testbenches/register_file_tb.vvp hardware/testbenches/register_file_tb.v hardware/src/register_file.v
//   vvp hardware/testbenches/register_file_tb.vvp
//
// WHAT THIS TESTS:
//   1. Reset clears all registers to 0
//   2. Write + read-back works for all 7 writable registers (R1–R7)
//   3. R0 is hardwired to 0 — writes to R0 are silently discarded
//   4. Write enable = 0 means no write occurs (register holds previous value)
//   5. Two read ports work independently and simultaneously
//   6. Reading a register immediately after a write returns the NEW value
//      (one cycle later — not the same cycle, because writes are clocked)
//
// READING THE WAVEFORM IN GTKWAVE:
// After running, open waveforms/register_file.vcd in GTKWave.
//   - Drag clk, rst, wr_en, wr_addr, wr_data, rd_addr1, rd_data1 into the
//     signal view.
//   - You'll see clk toggling. Notice that rd_data1 updates ONE CYCLE AFTER
//     the write, not instantly. The write takes effect on the posedge, and
//     the read reflects the new value from that point forward.
//   - This 1-cycle write latency is fundamental to clocked storage.
//
// =============================================================================

`timescale 1ns/1ps

module register_file_tb;

    // ---- Signals ------------------------------------------------------------
    reg        clk;
    reg        rst;
    reg  [2:0] rd_addr1, rd_addr2;
    wire [15:0] rd_data1, rd_data2;
    reg  [2:0] wr_addr;
    reg  [15:0] wr_data;
    reg        wr_en;

    // ---- Instantiate the register file --------------------------------------
    register_file uut (
        .clk(clk),
        .rst(rst),
        .rd_addr1(rd_addr1), .rd_data1(rd_data1),
        .rd_addr2(rd_addr2), .rd_data2(rd_data2),
        .wr_addr(wr_addr),
        .wr_data(wr_data),
        .wr_en(wr_en)
    );

    // ---- Clock generation ---------------------------------------------------
    // The clock toggles every 5ns → period = 10ns → 100 MHz
    // `initial` runs once. The `forever` loop keeps it running.
    // This is standard testbench clock generation.
    initial clk = 0;
    always #5 clk = ~clk;  // toggle every 5 time units

    // ---- Helper task --------------------------------------------------------
    integer pass_count, fail_count, test_num;

    task check16;
        input [127:0] label;
        input [15:0]  got;
        input [15:0]  expected;
        begin
            test_num = test_num + 1;
            if (got === expected) begin
                $display("  PASS [%0d] %s = %0d", test_num, label, got);
                pass_count = pass_count + 1;
            end else begin
                $display("  FAIL [%0d] %s: got %0d, expected %0d", test_num, label, got, expected);
                fail_count = fail_count + 1;
            end
        end
    endtask

    // ---- Convenience: wait for N rising clock edges -------------------------
    task tick;
        input integer n;
        integer j;
        begin
            for (j = 0; j < n; j = j + 1)
                @(posedge clk); #1; // #1 gives combinational outputs time to settle
        end
    endtask

    // ---- Main test ----------------------------------------------------------
    initial begin
        $dumpfile("register_file.vcd");
        $dumpvars(0, register_file_tb);

        pass_count = 0; fail_count = 0; test_num = 0;
        wr_en = 0; wr_addr = 0; wr_data = 0;
        rd_addr1 = 0; rd_addr2 = 0;

        $display("============================================");
        $display("  NexaCPU Register File Testbench — M2");
        $display("============================================");

        // ---- Test 1: Reset --------------------------------------------------
        $display("\n-- Reset --");
        rst = 1;
        tick(2); // hold reset for 2 cycles
        rst = 0;
        // After reset, read all registers — all should be 0
        begin : reset_check
            integer r;
            for (r = 0; r < 8; r = r + 1) begin
                rd_addr1 = r;
                #1; // let combinational read settle
                test_num = test_num + 1;
                if (rd_data1 === 16'd0) begin
                    $display("  PASS [%0d] After reset: R%0d = 0", test_num, r);
                    pass_count = pass_count + 1;
                end else begin
                    $display("  FAIL [%0d] After reset: R%0d = %0d (expected 0)", test_num, r, rd_data1);
                    fail_count = fail_count + 1;
                end
            end
        end

        // ---- Test 2: Write to R1–R7, read back ----------------------------
        $display("\n-- Write and read back (R1-R7) --");
        begin : write_check
            integer r;
            for (r = 1; r < 8; r = r + 1) begin
                // Set up write inputs BEFORE the clock edge
                wr_addr = r;
                wr_data = r * 10;   // R1=10, R2=20, ..., R7=70
                wr_en   = 1;
                tick(1);            // clock edge captures the write
                wr_en   = 0;        // de-assert write enable

                // Now read it back
                rd_addr1 = r;
                #1; // settle
                test_num = test_num + 1;
                if (rd_data1 === r * 10) begin
                    $display("  PASS [%0d] R%0d = %0d", test_num, r, rd_data1);
                    pass_count = pass_count + 1;
                end else begin
                    $display("  FAIL [%0d] R%0d: got %0d, expected %0d",
                              test_num, r, rd_data1, r*10);
                    fail_count = fail_count + 1;
                end
            end
        end

        // ---- Test 3: R0 hardwired to zero -----------------------------------
        $display("\n-- R0 hardwired to zero --");
        wr_addr = 3'd0; wr_data = 16'hABCD; wr_en = 1;
        tick(1);
        wr_en = 0;
        rd_addr1 = 3'd0; #1;
        check16("R0 after write attempt", rd_data1, 16'd0);

        // ---- Test 4: Write enable = 0 means no write ------------------------
        $display("\n-- Write-enable gating --");
        rd_addr1 = 3'd1; #1;
        begin : we_check
            reg [15:0] before;
            before = rd_data1;           // capture current R1 value (should be 10)
            wr_addr = 3'd1; wr_data = 16'hFFFF; wr_en = 0;  // en=0!
            tick(1);
            wr_en = 0;
            rd_addr1 = 3'd1; #1;
            check16("R1 unchanged when wr_en=0", rd_data1, before);
        end

        // ---- Test 5: Two read ports simultaneously --------------------------
        $display("\n-- Dual read ports --");
        // R1=10, R2=20 from earlier writes
        rd_addr1 = 3'd1; rd_addr2 = 3'd2; #1;
        check16("Port1 R1", rd_data1, 16'd10);
        check16("Port2 R2", rd_data2, 16'd20);
        // Both ports at same address return same value
        rd_addr1 = 3'd3; rd_addr2 = 3'd3; #1;
        begin : same_addr
            test_num = test_num + 1;
            if (rd_data1 === rd_data2) begin
                $display("  PASS [%0d] Both ports R3 agree: %0d", test_num, rd_data1);
                pass_count = pass_count + 1;
            end else begin
                $display("  FAIL [%0d] Port mismatch: p1=%0d p2=%0d", test_num, rd_data1, rd_data2);
                fail_count = fail_count + 1;
            end
        end

        // ---- Test 6: Overwrite a register -----------------------------------
        $display("\n-- Overwrite R3 --");
        wr_addr = 3'd3; wr_data = 16'd999; wr_en = 1;
        tick(1); wr_en = 0;
        rd_addr1 = 3'd3; #1;
        check16("R3 overwritten to 999", rd_data1, 16'd999);

        // ---- Test 7: Reset clears everything --------------------------------
        $display("\n-- Reset clears all --");
        rst = 1; tick(1); rst = 0;
        begin : reset2
            integer r;
            for (r = 0; r < 8; r = r + 1) begin
                rd_addr1 = r; #1;
                test_num = test_num + 1;
                if (rd_data1 === 16'd0) begin
                    $display("  PASS [%0d] R%0d cleared to 0 after reset", test_num, r);
                    pass_count = pass_count + 1;
                end else begin
                    $display("  FAIL [%0d] R%0d = %0d after reset (expected 0)", test_num, r, rd_data1);
                    fail_count = fail_count + 1;
                end
            end
        end

        // ---- Final report ---------------------------------------------------
        $display("\n============================================");
        $display("  Results: %0d passed, %0d failed (of %0d)",
                  pass_count, fail_count, test_num);
        if (fail_count == 0)
            $display("  ALL TESTS PASSED — Register File verified. ✓");
        else
            $display("  SOME TESTS FAILED — check above.");
        $display("============================================");

        $finish;
    end

endmodule

waveforms/register_file.vcd
$date
	Wed Jul 22 00:34:02 2026
$end
$version
	Icarus Verilog
$end
$timescale
	1ps
$end
$scope module register_file_tb $end
$var wire 16 ! rd_data2 [15:0] $end
$var wire 16 " rd_data1 [15:0] $end
$var reg 1 # clk $end
$var reg 3 $ rd_addr1 [2:0] $end
$var reg 3 % rd_addr2 [2:0] $end
$var reg 1 & rst $end
$var reg 3 ' wr_addr [2:0] $end
$var reg 16 ( wr_data [15:0] $end
$var reg 1 ) wr_en $end
$var integer 32 * fail_count [31:0] $end
$var integer 32 + pass_count [31:0] $end
$var integer 32 , test_num [31:0] $end
$scope module uut $end
$var wire 1 # clk $end
$var wire 3 - rd_addr1 [2:0] $end
$var wire 3 . rd_addr2 [2:0] $end
$var wire 1 & rst $end
$var wire 3 / wr_addr [2:0] $end
$var wire 16 0 wr_data [15:0] $end
$var wire 1 ) wr_en $end
$var wire 16 1 rd_data2 [15:0] $end
$var wire 16 2 rd_data1 [15:0] $end
$var integer 32 3 i [31:0] $end
$upscope $end
$scope begin reset2 $end
$var integer 32 4 r [31:0] $end
$upscope $end
$scope begin reset_check $end
$var integer 32 5 r [31:0] $end
$upscope $end
$scope begin same_addr $end
$upscope $end
$scope begin we_check $end
$var reg 16 6 before [15:0] $end
$upscope $end
$scope begin write_check $end
$var integer 32 7 r [31:0] $end
$upscope $end
$scope task check16 $end
$var reg 16 8 expected [15:0] $end
$var reg 16 9 got [15:0] $end
$var reg 128 : label [127:0] $end
$upscope $end
$scope task tick $end
$var integer 32 ; j [31:0] $end
$var integer 32 < n [31:0] $end
$upscope $end
$upscope $end
$enddefinitions $end
$comment Show the parameter values. $end
$dumpall
$end
#0
$dumpvars
b10 <
b0 ;
bx :
bx 9
bx 8
bx 7
bx 6
bx 5
bx 4
bx 3
b0 2
b0 1
b0 0
b0 /
b0 .
b0 -
b0 ,
b0 +
b0 *
0)
b0 (
b0 '
1&
b0 %
b0 $
0#
b0 "
b0 !
$end
#5000
b1000 3
b1 ;
1#
#10000
0#
#15000
b10 ;
b1000 3
1#
#16000
b0 5
0&
#17000
b1 $
b1 -
b1 5
b1 +
b1 ,
#18000
b10 $
b10 -
b10 5
b10 +
b10 ,
#19000
b11 $
b11 -
b11 5
b11 +
b11 ,
#20000
b100 $
b100 -
b100 5
b100 +
b100 ,
0#
#21000
b101 $
b101 -
b101 5
b101 +
b101 ,
#22000
b110 $
b110 -
b110 5
b110 +
b110 ,
#23000
b111 $
b111 -
b111 5
b111 +
b111 ,
#24000
b0 ;
b1 <
1)
b1010 (
b1010 0
b1 '
b1 /
b1 7
b1000 5
b1000 +
b1000 ,
#25000
b1 ;
1#
#26000
b1010 "
b1010 2
b1 $
b1 -
0)
#27000
b0 ;
1)
b10100 (
b10100 0
b10 '
b10 /
b10 7
b1001 +
b1001 ,
#30000
0#
#35000
b1 ;
1#
#36000
b10100 "
b10100 2
b10 $
b10 -
0)
#37000
b0 ;
1)
b11110 (
b11110 0
b11 '
b11 /
b11 7
b1010 +
b1010 ,
#40000
0#
#45000
b1 ;
1#
#46000
b11110 "
b11110 2
b11 $
b11 -
0)
#47000
b0 ;
1)
b101000 (
b101000 0
b100 '
b100 /
b100 7
b1011 +
b1011 ,
#50000
0#
#55000
b1 ;
1#
#56000
b101000 "
b101000 2
b100 $
b100 -
0)
#57000
b0 ;
1)
b110010 (
b110010 0
b101 '
b101 /
b101 7
b1100 +
b1100 ,
#60000
0#
#65000
b1 ;
1#
#66000
b110010 "
b110010 2
b101 $
b101 -
0)
#67000
b0 ;
1)
b111100 (
b111100 0
b110 '
b110 /
b110 7
b1101 +
b1101 ,
#70000
0#
#75000
b1 ;
1#
#76000
b111100 "
b111100 2
b110 $
b110 -
0)
#77000
b0 ;
1)
b1000110 (
b1000110 0
b111 '
b111 /
b111 7
b1110 +
b1110 ,
#80000
0#
#85000
b1 ;
1#
#86000
b1000110 "
b1000110 2
b111 $
b111 -
0)
#87000
b0 ;
1)
b1010101111001101 (
b1010101111001101 0
b0 '
b0 /
b1000 7
b1111 +
b1111 ,
#90000
0#
#95000
b1 ;
1#
#96000
b0 "
b0 2
b0 $
b0 -
0)
#97000
b1010 "
b1010 2
b1 $
b1 -
b10000 +
b10000 ,
b0 8
b0 9
b1100101011100100010000001110111011100100110100101110100011001010010000001100001011101000111010001100101011011010111000001110100 :
#98000
b0 ;
b1111111111111111 (
b1111111111111111 0
b1 '
b1 /
b1010 6
#100000
0#
#105000
b1 ;
1#
#107000
b10100 !
b10100 1
b10 %
b10 .
b10001 +
b10001 ,
b1010 8
b1010 9
b1100111011001010110010000100000011101110110100001100101011011100010000001110111011100100101111101100101011011100011110100110000 :
#108000
b11110 !
b11110 1
b11110 "
b11110 2
b11 %
b11 .
b11 $
b11 -
b10100 8
b10100 9
b10011 +
b10011 ,
b101000001101111011100100111010000110010001000000101001000110010 :
#109000
b0 ;
1)
b1111100111 (
b1111100111 0
b11 '
b11 /
b10100 +
b10100 ,
#110000
0#
#115000
b1111100111 "
b1111100111 2
b1111100111 !
b1111100111 1
b1 ;
1#
#116000
0)
#117000
b0 ;
1&
b10101 +
b10101 ,
b1111100111 8
b1111100111 9
b1100101011100100111011101110010011010010111010001110100011001010110111000100000011101000110111100100000001110010011100100111001 :
#120000
0#
#125000
b0 "
b0 2
b0 !
b0 1
b1000 3
b1 ;
1#
#126000
b0 $
b0 -
b0 4
0&
#127000
b1 $
b1 -
b1 4
b10110 +
b10110 ,
#128000
b10 $
b10 -
b10 4
b10111 +
b10111 ,
#129000
b11 $
b11 -
b11 4
b11000 +
b11000 ,
#130000
b100 $
b100 -
b100 4
b11001 +
b11001 ,
0#
#131000
b101 $
b101 -
b101 4
b11010 +
b11010 ,
#132000
b110 $
b110 -
b110 4
b11011 +
b11011 ,
#133000
b111 $
b111 -
b111 4
b11100 +
b11100 ,
#134000
b1000 4
b11101 +
b11101 ,
